milkviz/__init__.py
milkviz/_bubble.py
milkviz/_cell_map.py
milkviz/_clustermap.py
milkviz/_dot_matrix.py
milkviz/_graph.py
milkviz/_stacked_bar.py
milkviz/_upset.py
milkviz/_venn.py
milkviz/colormap.py
milkviz/utils.py
milkviz-0.6.0.dist-info/LICENSE
milkviz-0.6.0.dist-info/WHEEL
milkviz-0.6.0.dist-info/METADATA
milkviz-0.6.0.dist-info/RECORD
