Metadata-Version: 2.1
Name: milkviz
Version: 0.6.0
Summary: Self-opinionated miscellaneous visualizations library in python
Home-page: https://github.com/Mr-Milk/milkviz
License: MIT
Author: Mr-Milk
Author-email: yb97643@um.edu.mo
Requires-Python: >=3.8,<4.0
Classifier: Framework :: Matplotlib
Classifier: Intended Audience :: Developers
Classifier: Intended Audience :: Science/Research
Classifier: License :: OSI Approved :: MIT License
Classifier: Programming Language :: Python :: 3
Classifier: Programming Language :: Python :: 3.8
Classifier: Programming Language :: Python :: 3.9
Classifier: Programming Language :: Python :: 3.10
Classifier: Programming Language :: Python :: 3
Classifier: Topic :: Scientific/Engineering :: Visualization
Provides-Extra: all
Requires-Dist: legendkit (>=0.2.4,<0.3.0)
Requires-Dist: matplotlib (>=3.5,<4.0)
Requires-Dist: matplotlib-venn (>=0.11.7,<0.12.0); extra == "all"
Requires-Dist: networkx (>=2.8.6,<3.0.0); extra == "all"
Requires-Dist: pandas (>=1.5.0,<2.0.0)
Project-URL: Repository, https://github.com/Mr-Milk/milkviz
